{
  "contribution_id": "1686bf13e9184faf_20260118_030110",
  "poem_id": "P007",
  "title": "ФИРОР",
  "metadata": {
    "submission_date": "2026-01-18T03:01:10.418187",
    "contributor": {
      "anonymous": true
    },
    "software_version": "2.1.0",
    "content_hash": "1686bf13e9184faf",
    "source_language": "tg",
    "license_accepted": true
  },
  "raw_text": "ФИРОР\n\nКасе омад,\nки набзи ман\nдар садои пояш мезад\nКасе омад,\nки овози абадият\nдар ҳанҷараи гулӯяш месӯхт\nНигоҳ кард\nба иртиботи шикастаи\nман бо ман.\nТанҳо шудам,\nто зиндагиро дар хоби марг тасвир кунам...\n\nЭй марг\nфардо пушти болҳои ту хоҳад монд\nва кабутар аз рӯи дастҳои ту бенишон\n\nКасе омад,\nки сояи дасташ чатри оромиш буд.\nВа сурогаи роҳи фирор овард,\nБо қатораҳои фаромӯшӣ\n\nЧи ҳатти сояранге дар чабинам,\nНавои ҳаста- борони ҳазинам.\n\nЗи фардоҳо чи мепурсӣ сурогам,\nГиреҳ андар нафасҳои заминам.\n\nЧи мегӯй ту бозори замонро,\nПашизи бебаҳо пеши нигинам.\n\nНа лабханадеву гармое, на ишқе,\nҲамин дард аст, гӯё дар каминам.\n\nБа ин болеву парвозе, ки дорам,\nКуҷо боло?, ҳанӯзам дар заминам.\n\nСурогӣ осмони интиҳо ку?\nҲанӯзам зарраи хоки қадимам.\n\nҒуруби лолаи сабри ман ин аст,\nЧи мепурсӣ, чаро ҳоло чунинам.",
  "normalized_text": "ФИРОР\n\nКасе омад,\nки набзи ман\nдар садои пояш мезад\nКасе омад,\nки овози абадият\nдар ҳанҷараи гулӯяш месӯхт\nНигоҳ кард\nба иртиботи шикастаи\nман бо ман.\nТанҳо шудам,\nто зиндагиро дар хоби марг тасвир кунам...\n\nЭй марг\nфардо пушти болҳои ту хоҳад монд\nва кабутар аз рӯи дастҳои ту бенишон\n\nКасе омад,\nки сояи дасташ чатри оромиш буд.\nВа сурогаи роҳи фирор овард,\nБо қатораҳои фаромӯшӣ\n\nЧи ҳатти сояранге дар чабинам,\nНавои ҳаста- борони ҳазинам.\n\nЗи фардоҳо чи мепурсӣ сурогам,\nГиреҳ андар нафасҳои заминам.\n\nЧи мегӯй ту бозори замонро,\nПашизи бебаҳо пеши нигинам.\n\nНа лабханадеву гармое, на ишқе,\nҲамин дард аст, гӯё дар каминам.\n\nБа ин болеву парвозе, ки дорам,\nКуҷо боло?, ҳанӯзам дар заминам.\n\nСурогӣ осмони интиҳо ку?\nҲанӯзам зарраи хоки қадимам.\n\nҒуруби лолаи сабри ман ин аст,\nЧи мепурсӣ, чаро ҳоло чунинам.",
  "analysis": {
    "structural": {
      "lines": 33,
      "syllables_per_line": [
        0,
        4,
        4,
        8,
        4,
        8,
        10,
        3,
        9,
        3,
        4,
        13,
        1,
        11,
        14,
        4,
        12,
        11,
        10,
        11,
        11,
        11,
        11,
        10,
        11,
        12,
        10,
        11,
        11,
        10,
        11,
        11,
        11
      ],
      "syllable_patterns": [
        [],
        [
          {
            "text": "а",
            "weight": "SyllableWeight.LIGHT",
            "phonetic": "a",
            "position": 0,
            "confidence": 0.85,
            "stress_level": 0
          },
          {
            "text": "се",
            "weight": "SyllableWeight.LIGHT",
            "phonetic": "se",
            "position": 1,
            "confidence": 0.85,
            "stress_level": 2
          },
          {
            "text": "ом",
            "weight": "SyllableWeight.HEAVY",
            "phonetic": "om",
            "position": 2,
            "confidence": 0.85,
            "stress_level": 0
          },
          {
            "text": "ад",
            "weight": "SyllableWeight.HEAVY",
            "phonetic": "ad",
            "position": 3,
            "confidence": 0.85,
            "stress_level": 2
          }
        ],
        [
          {
            "text": "ки",
            "weight": "SyllableWeight.LIGHT",
            "phonetic": "ki",
            "position": 0,
            "confidence": 0.85,
            "stress_level": 2
          },
          {
            "text": "наб",
            "weight": "SyllableWeight.HEAVY",
            "phonetic": "nab",
            "position": 1,
            "confidence": 0.85,
            "stress_level": 0
          },
          {
            "text": "зи",
            "weight": "SyllableWeight.LIGHT",
            "phonetic": "zi",
            "position": 2,
            "confidence": 0.85,
            "stress_level": 2
          },
          {
            "text": "ман",
            "weight": "SyllableWeight.HEAVY",
            "phonetic": "man",
            "position": 3,
            "confidence": 0.85,
            "stress_level": 2
          }
        ],
        [
          {
            "text": "дар",
            "weight": "SyllableWeight.HEAVY",
            "phonetic": "dar",
            "position": 0,
            "confidence": 0.85,
            "stress_level": 2
          },
          {
            "text": "са",
            "weight": "SyllableWeight.LIGHT",
            "phonetic": "sa",
            "position": 1,
            "confidence": 0.85,
            "stress_level": 0
          },
          {
            "text": "до",
            "weight": "SyllableWeight.LIGHT",
            "phonetic": "do",
            "position": 2,
            "confidence": 0.85,
            "stress_level": 0
          },
          {
            "text": "и",
            "weight": "SyllableWeight.LIGHT",
            "phonetic": "i",
            "position": 3,
            "confidence": 0.85,
            "stress_level": 2
          },
          {
            "text": "по",
            "weight": "SyllableWeight.LIGHT",
            "phonetic": "po",
            "position": 4,
            "confidence": 0.85,
            "stress_level": 0
          },
          {
            "text": "яш",
            "weight": "SyllableWeight.HEAVY",
            "phonetic": "jaʃ",
            "position": 5,
            "confidence": 0.85,
            "stress_level": 2
          },
          {
            "text": "ме",
            "weight": "SyllableWeight.LIGHT",
            "phonetic": "me",
            "position": 6,
            "confidence": 0.85,
            "stress_level": 0
          },
          {
            "text": "зад",
            "weight": "SyllableWeight.HEAVY",
            "phonetic": "zad",
            "position": 7,
            "confidence": 0.85,
            "stress_level": 2
          }
        ],
        [
          {
            "text": "а",
            "weight": "SyllableWeight.LIGHT",
            "phonetic": "a",
            "position": 0,
            "confidence": 0.85,
            "stress_level": 0
          },
          {
            "text": "се",
            "weight": "SyllableWeight.LIGHT",
            "phonetic": "se",
            "position": 1,
            "confidence": 0.85,
            "stress_level": 2
          },
          {
            "text": "ом",
            "weight": "SyllableWeight.HEAVY",
            "phonetic": "om",
            "position": 2,
            "confidence": 0.85,
            "stress_level": 0
          },
          {
            "text": "ад",
            "weight": "SyllableWeight.HEAVY",
            "phonetic": "ad",
            "position": 3,
            "confidence": 0.85,
            "stress_level": 2
          }
        ],
        [
          {
            "text": "ки",
            "weight": "SyllableWeight.LIGHT",
            "phonetic": "ki",
            "position": 0,
            "confidence": 0.85,
            "stress_level": 2
          },
          {
            "text": "ов",
            "weight": "SyllableWeight.HEAVY",
            "phonetic": "ov",
            "position": 1,
            "confidence": 0.85,
            "stress_level": 0
          },
          {
            "text": "о",
            "weight": "SyllableWeight.LIGHT",
            "phonetic": "o",
            "position": 2,
            "confidence": 0.85,
            "stress_level": 0
          },
          {
            "text": "зи",
            "weight": "SyllableWeight.LIGHT",
            "phonetic": "zi",
            "position": 3,
            "confidence": 0.85,
            "stress_level": 2
          },
          {
            "text": "а",
            "weight": "SyllableWeight.LIGHT",
            "phonetic": "a",
            "position": 4,
            "confidence": 0.85,
            "stress_level": 0
          },
          {
            "text": "ба",
            "weight": "SyllableWeight.LIGHT",
            "phonetic": "ba",
            "position": 5,
            "confidence": 0.85,
            "stress_level": 0
          },
          {
            "text": "ди",
            "weight": "SyllableWeight.LIGHT",
            "phonetic": "di",
            "position": 6,
            "confidence": 0.85,
            "stress_level": 0
          },
          {
            "text": "ят",
            "weight": "SyllableWeight.HEAVY",
            "phonetic": "jat",
            "position": 7,
            "confidence": 0.85,
            "stress_level": 2
          }
        ],
        [
          {
            "text": "дар",
            "weight": "SyllableWeight.HEAVY",
            "phonetic": "dar",
            "position": 0,
            "confidence": 0.85,
            "stress_level": 2
          },
          {
            "text": "ҳан",
            "weight": "SyllableWeight.HEAVY",
            "phonetic": "han",
            "position": 1,
            "confidence": 0.85,
            "stress_level": 0
          },
          {
            "text": "ҷар",
            "weight": "SyllableWeight.HEAVY",
            "phonetic": "ʤar",
            "position": 2,
            "confidence": 0.85,
            "stress_level": 0
          },
          {
            "text": "а",
            "weight": "SyllableWeight.LIGHT",
            "phonetic": "a",
            "position": 3,
            "confidence": 0.85,
            "stress_level": 0
          },
          {
            "text": "и",
            "weight": "SyllableWeight.LIGHT",
            "phonetic": "i",
            "position": 4,
            "confidence": 0.85,
            "stress_level": 2
          },
          {
            "text": "гул",
            "weight": "SyllableWeight.HEAVY",
            "phonetic": "gul",
            "position": 5,
            "confidence": 0.85,
            "stress_level": 0
          },
          {
            "text": "ӯ",
            "weight": "SyllableWeight.HEAVY",
            "phonetic": "uː",
            "position": 6,
            "confidence": 0.85,
            "stress_level": 0
          },
          {
            "text": "яш",
            "weight": "SyllableWeight.HEAVY",
            "phonetic": "jaʃ",
            "position": 7,
            "confidence": 0.85,
            "stress_level": 2
          },
          {
            "text": "ме",
            "weight": "SyllableWeight.LIGHT",
            "phonetic": "me",
            "position": 8,
            "confidence": 0.85,
            "stress_level": 0
          },
          {
            "text": "сӯхт",
            "weight": "SyllableWeight.HEAVY",
            "phonetic": "suːxt",
            "position": 9,
            "confidence": 0.85,
            "stress_level": 2
          }
        ],
        [
          {
            "text": "и",
            "weight": "SyllableWeight.LIGHT",
            "phonetic": "i",
            "position": 0,
            "confidence": 0.85,
            "stress_level": 0
          },
          {
            "text": "гоҳ",
            "weight": "SyllableWeight.HEAVY",
            "phonetic": "goh",
            "position": 1,
            "confidence": 0.85,
            "stress_level": 2
          },
          {
            "text": "кард",
            "weight": "SyllableWeight.HEAVY",
            "phonetic": "kard",
            "position": 2,
            "confidence": 0.85,
            "stress_level": 2
          }
        ],
        [
          {
            "text": "ба",
            "weight": "SyllableWeight.LIGHT",
            "phonetic": "ba",
            "position": 0,
            "confidence": 0.85,
            "stress_level": 2
          },
          {
            "text": "ир",
            "weight": "SyllableWeight.HEAVY",
            "phonetic": "ir",
            "position": 1,
            "confidence": 0.85,
            "stress_level": 0
          },
          {
            "text": "ти",
            "weight": "SyllableWeight.LIGHT",
            "phonetic": "ti",
            "position": 2,
            "confidence": 0.85,
            "stress_level": 0
          },
          {
            "text": "бо",
            "weight": "SyllableWeight.LIGHT",
            "phonetic": "bo",
            "position": 3,
            "confidence": 0.85,
            "stress_level": 0
          },
          {
            "text": "ти",
            "weight": "SyllableWeight.LIGHT",
            "phonetic": "ti",
            "position": 4,
            "confidence": 0.85,
            "stress_level": 2
          },
          {
            "text": "ши",
            "weight": "SyllableWeight.LIGHT",
            "phonetic": "ʃi",
            "position": 5,
            "confidence": 0.85,
            "stress_level": 0
          },
          {
            "text": "кас",
            "weight": "SyllableWeight.HEAVY",
            "phonetic": "kas",
            "position": 6,
            "confidence": 0.85,
            "stress_level": 0
          },
          {
            "text": "та",
            "weight": "SyllableWeight.LIGHT",
            "phonetic": "ta",
            "position": 7,
            "confidence": 0.85,
            "stress_level": 0
          },
          {
            "text": "и",
            "weight": "SyllableWeight.LIGHT",
            "phonetic": "i",
            "position": 8,
            "confidence": 0.85,
            "stress_level": 2
          }
        ],
        [
          {
            "text": "ман",
            "weight": "SyllableWeight.HEAVY",
            "phonetic": "man",
            "position": 0,
            "confidence": 0.85,
            "stress_level": 2
          },
          {
            "text": "бо",
            "weight": "SyllableWeight.LIGHT",
            "phonetic": "bo",
            "position": 1,
            "confidence": 0.85,
            "stress_level": 2
          },
          {
            "text": "ман",
            "weight": "SyllableWeight.HEAVY",
            "phonetic": "man",
            "position": 2,
            "confidence": 0.85,
            "stress_level": 2
          }
        ],
        [
          {
            "text": "ан",
            "weight": "SyllableWeight.HEAVY",
            "phonetic": "an",
            "position": 0,
            "confidence": 0.85,
            "stress_level": 0
          },
          {
            "text": "ҳо",
            "weight": "SyllableWeight.LIGHT",
            "phonetic": "ho",
            "position": 1,
            "confidence": 0.85,
            "stress_level": 2
          },
          {
            "text": "шу",
            "weight": "SyllableWeight.LIGHT",
            "phonetic": "ʃu",
            "position": 2,
            "confidence": 0.85,
            "stress_level": 0
          },
          {
            "text": "дам",
            "weight": "SyllableWeight.HEAVY",
            "phonetic": "dam",
            "position": 3,
            "confidence": 0.85,
            "stress_level": 2
          }
        ],
        [
          {
            "text": "то",
            "weight": "SyllableWeight.LIGHT",
            "phonetic": "to",
            "position": 0,
            "confidence": 0.85,
            "stress_level": 2
          },
          {
            "text": "зин",
            "weight": "SyllableWeight.HEAVY",
            "phonetic": "zin",
            "position": 1,
            "confidence": 0.85,
            "stress_level": 0
          },
          {
            "text": "да",
            "weight": "SyllableWeight.LIGHT",
            "phonetic": "da",
            "position": 2,
            "confidence": 0.85,
            "stress_level": 0
          },
          {
            "text": "гир",
            "weight": "SyllableWeight.HEAVY",
            "phonetic": "gir",
            "position": 3,
            "confidence": 0.85,
            "stress_level": 0
          },
          {
            "text": "о",
            "weight": "SyllableWeight.LIGHT",
            "phonetic": "o",
            "position": 4,
            "confidence": 0.85,
            "stress_level": 2
          },
          {
            "text": "дар",
            "weight": "SyllableWeight.HEAVY",
            "phonetic": "dar",
            "position": 5,
            "confidence": 0.85,
            "stress_level": 2
          },
          {
            "text": "хо",
            "weight": "SyllableWeight.LIGHT",
            "phonetic": "xo",
            "position": 6,
            "confidence": 0.85,
            "stress_level": 0
          },
          {
            "text": "би",
            "weight": "SyllableWeight.LIGHT",
            "phonetic": "bi",
            "position": 7,
            "confidence": 0.85,
            "stress_level": 2
          },
          {
            "text": "марг",
            "weight": "SyllableWeight.HEAVY",
            "phonetic": "marg",
            "position": 8,
            "confidence": 0.85,
            "stress_level": 2
          },
          {
            "text": "тасв",
            "weight": "SyllableWeight.HEAVY",
            "phonetic": "tasv",
            "position": 9,
            "confidence": 0.85,
            "stress_level": 0
          },
          {
            "text": "ир",
            "weight": "SyllableWeight.HEAVY",
            "phonetic": "ir",
            "position": 10,
            "confidence": 0.85,
            "stress_level": 2
          },
          {
            "text": "кун",
            "weight": "SyllableWeight.HEAVY",
            "phonetic": "kun",
            "position": 11,
            "confidence": 0.85,
            "stress_level": 0
          },
          {
            "text": "ам",
            "weight": "SyllableWeight.HEAVY",
            "phonetic": "am",
            "position": 12,
            "confidence": 0.85,
            "stress_level": 2
          }
        ],
        [
          {
            "text": "марг",
            "weight": "SyllableWeight.HEAVY",
            "phonetic": "marg",
            "position": 0,
            "confidence": 0.85,
            "stress_level": 2
          }
        ],
        [
          {
            "text": "фар",
            "weight": "SyllableWeight.HEAVY",
            "phonetic": "far",
            "position": 0,
            "confidence": 0.85,
            "stress_level": 0
          },
          {
            "text": "до",
            "weight": "SyllableWeight.LIGHT",
            "phonetic": "do",
            "position": 1,
            "confidence": 0.85,
            "stress_level": 2
          },
          {
            "text": "пуш",
            "weight": "SyllableWeight.HEAVY",
            "phonetic": "puʃ",
            "position": 2,
            "confidence": 0.85,
            "stress_level": 0
          },
          {
            "text": "ти",
            "weight": "SyllableWeight.LIGHT",
            "phonetic": "ti",
            "position": 3,
            "confidence": 0.85,
            "stress_level": 2
          },
          {
            "text": "бол",
            "weight": "SyllableWeight.HEAVY",
            "phonetic": "bol",
            "position": 4,
            "confidence": 0.85,
            "stress_level": 0
          },
          {
            "text": "ҳо",
            "weight": "SyllableWeight.LIGHT",
            "phonetic": "ho",
            "position": 5,
            "confidence": 0.85,
            "stress_level": 0
          },
          {
            "text": "и",
            "weight": "SyllableWeight.LIGHT",
            "phonetic": "i",
            "position": 6,
            "confidence": 0.85,
            "stress_level": 2
          },
          {
            "text": "ту",
            "weight": "SyllableWeight.LIGHT",
            "phonetic": "tu",
            "position": 7,
            "confidence": 0.85,
            "stress_level": 2
          },
          {
            "text": "хо",
            "weight": "SyllableWeight.LIGHT",
            "phonetic": "xo",
            "position": 8,
            "confidence": 0.85,
            "stress_level": 0
          },
          {
            "text": "ҳад",
            "weight": "SyllableWeight.HEAVY",
            "phonetic": "had",
            "position": 9,
            "confidence": 0.85,
            "stress_level": 2
          },
          {
            "text": "монд",
            "weight": "SyllableWeight.HEAVY",
            "phonetic": "mond",
            "position": 10,
            "confidence": 0.85,
            "stress_level": 2
          }
        ],
        [
          {
            "text": "ва",
            "weight": "SyllableWeight.LIGHT",
            "phonetic": "va",
            "position": 0,
            "confidence": 0.85,
            "stress_level": 2
          },
          {
            "text": "ка",
            "weight": "SyllableWeight.LIGHT",
            "phonetic": "ka",
            "position": 1,
            "confidence": 0.85,
            "stress_level": 0
          },
          {
            "text": "бу",
            "weight": "SyllableWeight.LIGHT",
            "phonetic": "bu",
            "position": 2,
            "confidence": 0.85,
            "stress_level": 0
          },
          {
            "text": "тар",
            "weight": "SyllableWeight.HEAVY",
            "phonetic": "tar",
            "position": 3,
            "confidence": 0.85,
            "stress_level": 2
          },
          {
            "text": "аз",
            "weight": "SyllableWeight.HEAVY",
            "phonetic": "az",
            "position": 4,
            "confidence": 0.85,
            "stress_level": 2
          },
          {
            "text": "рӯ",
            "weight": "SyllableWeight.HEAVY",
            "phonetic": "ruː",
            "position": 5,
            "confidence": 0.85,
            "stress_level": 0
          },
          {
            "text": "и",
            "weight": "SyllableWeight.LIGHT",
            "phonetic": "i",
            "position": 6,
            "confidence": 0.85,
            "stress_level": 2
          },
          {
            "text": "даст",
            "weight": "SyllableWeight.HEAVY",
            "phonetic": "dast",
            "position": 7,
            "confidence": 0.85,
            "stress_level": 0
          },
          {
            "text": "ҳо",
            "weight": "SyllableWeight.LIGHT",
            "phonetic": "ho",
            "position": 8,
            "confidence": 0.85,
            "stress_level": 0
          },
          {
            "text": "и",
            "weight": "SyllableWeight.LIGHT",
            "phonetic": "i",
            "position": 9,
            "confidence": 0.85,
            "stress_level": 2
          },
          {
            "text": "ту",
            "weight": "SyllableWeight.LIGHT",
            "phonetic": "tu",
            "position": 10,
            "confidence": 0.85,
            "stress_level": 2
          },
          {
            "text": "бен",
            "weight": "SyllableWeight.HEAVY",
            "phonetic": "ben",
            "position": 11,
            "confidence": 0.85,
            "stress_level": 0
          },
          {
            "text": "и",
            "weight": "SyllableWeight.LIGHT",
            "phonetic": "i",
            "position": 12,
            "confidence": 0.85,
            "stress_level": 0
          },
          {
            "text": "шон",
            "weight": "SyllableWeight.HEAVY",
            "phonetic": "ʃon",
            "position": 13,
            "confidence": 0.85,
            "stress_level": 2
          }
        ],
        [
          {
            "text": "а",
            "weight": "SyllableWeight.LIGHT",
            "phonetic": "a",
            "position": 0,
            "confidence": 0.85,
            "stress_level": 0
          },
          {
            "text": "се",
            "weight": "SyllableWeight.LIGHT",
            "phonetic": "se",
            "position": 1,
            "confidence": 0.85,
            "stress_level": 2
          },
          {
            "text": "ом",
            "weight": "SyllableWeight.HEAVY",
            "phonetic": "om",
            "position": 2,
            "confidence": 0.85,
            "stress_level": 0
          },
          {
            "text": "ад",
            "weight": "SyllableWeight.HEAVY",
            "phonetic": "ad",
            "position": 3,
            "confidence": 0.85,
            "stress_level": 2
          }
        ],
        [
          {
            "text": "ки",
            "weight": "SyllableWeight.LIGHT",
            "phonetic": "ki",
            "position": 0,
            "confidence": 0.85,
            "stress_level": 2
          },
          {
            "text": "со",
            "weight": "SyllableWeight.LIGHT",
            "phonetic": "so",
            "position": 1,
            "confidence": 0.85,
            "stress_level": 0
          },
          {
            "text": "я",
            "weight": "SyllableWeight.LIGHT",
            "phonetic": "ja",
            "position": 2,
            "confidence": 0.85,
            "stress_level": 0
          },
          {
            "text": "и",
            "weight": "SyllableWeight.LIGHT",
            "phonetic": "i",
            "position": 3,
            "confidence": 0.85,
            "stress_level": 2
          },
          {
            "text": "дас",
            "weight": "SyllableWeight.HEAVY",
            "phonetic": "das",
            "position": 4,
            "confidence": 0.85,
            "stress_level": 0
          },
          {
            "text": "таш",
            "weight": "SyllableWeight.HEAVY",
            "phonetic": "taʃ",
            "position": 5,
            "confidence": 0.85,
            "stress_level": 2
          },
          {
            "text": "чатр",
            "weight": "SyllableWeight.HEAVY",
            "phonetic": "ʧatr",
            "position": 6,
            "confidence": 0.85,
            "stress_level": 0
          },
          {
            "text": "и",
            "weight": "SyllableWeight.LIGHT",
            "phonetic": "i",
            "position": 7,
            "confidence": 0.85,
            "stress_level": 2
          },
          {
            "text": "ор",
            "weight": "SyllableWeight.HEAVY",
            "phonetic": "or",
            "position": 8,
            "confidence": 0.85,
            "stress_level": 0
          },
          {
            "text": "ом",
            "weight": "SyllableWeight.HEAVY",
            "phonetic": "om",
            "position": 9,
            "confidence": 0.85,
            "stress_level": 0
          },
          {
            "text": "иш",
            "weight": "SyllableWeight.HEAVY",
            "phonetic": "iʃ",
            "position": 10,
            "confidence": 0.85,
            "stress_level": 2
          },
          {
            "text": "буд",
            "weight": "SyllableWeight.HEAVY",
            "phonetic": "bud",
            "position": 11,
            "confidence": 0.85,
            "stress_level": 2
          }
        ],
        [
          {
            "text": "а",
            "weight": "SyllableWeight.LIGHT",
            "phonetic": "a",
            "position": 0,
            "confidence": 0.85,
            "stress_level": 2
          },
          {
            "text": "сур",
            "weight": "SyllableWeight.HEAVY",
            "phonetic": "sur",
            "position": 1,
            "confidence": 0.85,
            "stress_level": 0
          },
          {
            "text": "о",
            "weight": "SyllableWeight.LIGHT",
            "phonetic": "o",
            "position": 2,
            "confidence": 0.85,
            "stress_level": 0
          },
          {
            "text": "га",
            "weight": "SyllableWeight.LIGHT",
            "phonetic": "ga",
            "position": 3,
            "confidence": 0.85,
            "stress_level": 0
          },
          {
            "text": "и",
            "weight": "SyllableWeight.LIGHT",
            "phonetic": "i",
            "position": 4,
            "confidence": 0.85,
            "stress_level": 2
          },
          {
            "text": "ро",
            "weight": "SyllableWeight.LIGHT",
            "phonetic": "ro",
            "position": 5,
            "confidence": 0.85,
            "stress_level": 0
          },
          {
            "text": "ҳи",
            "weight": "SyllableWeight.LIGHT",
            "phonetic": "hi",
            "position": 6,
            "confidence": 0.85,
            "stress_level": 2
          },
          {
            "text": "фир",
            "weight": "SyllableWeight.HEAVY",
            "phonetic": "fir",
            "position": 7,
            "confidence": 0.85,
            "stress_level": 0
          },
          {
            "text": "ор",
            "weight": "SyllableWeight.HEAVY",
            "phonetic": "or",
            "position": 8,
            "confidence": 0.85,
            "stress_level": 2
          },
          {
            "text": "ов",
            "weight": "SyllableWeight.HEAVY",
            "phonetic": "ov",
            "position": 9,
            "confidence": 0.85,
            "stress_level": 0
          },
          {
            "text": "ард",
            "weight": "SyllableWeight.HEAVY",
            "phonetic": "ard",
            "position": 10,
            "confidence": 0.85,
            "stress_level": 2
          }
        ],
        [
          {
            "text": "о",
            "weight": "SyllableWeight.LIGHT",
            "phonetic": "o",
            "position": 0,
            "confidence": 0.85,
            "stress_level": 2
          },
          {
            "text": "қа",
            "weight": "SyllableWeight.LIGHT",
            "phonetic": "qa",
            "position": 1,
            "confidence": 0.85,
            "stress_level": 0
          },
          {
            "text": "тор",
            "weight": "SyllableWeight.HEAVY",
            "phonetic": "tor",
            "position": 2,
            "confidence": 0.85,
            "stress_level": 0
          },
          {
            "text": "а",
            "weight": "SyllableWeight.LIGHT",
            "phonetic": "a",
            "position": 3,
            "confidence": 0.85,
            "stress_level": 0
          },
          {
            "text": "ҳо",
            "weight": "SyllableWeight.LIGHT",
            "phonetic": "ho",
            "position": 4,
            "confidence": 0.85,
            "stress_level": 0
          },
          {
            "text": "и",
            "weight": "SyllableWeight.LIGHT",
            "phonetic": "i",
            "position": 5,
            "confidence": 0.85,
            "stress_level": 2
          },
          {
            "text": "фар",
            "weight": "SyllableWeight.HEAVY",
            "phonetic": "far",
            "position": 6,
            "confidence": 0.85,
            "stress_level": 0
          },
          {
            "text": "ом",
            "weight": "SyllableWeight.HEAVY",
            "phonetic": "om",
            "position": 7,
            "confidence": 0.85,
            "stress_level": 0
          },
          {
            "text": "ӯ",
            "weight": "SyllableWeight.HEAVY",
            "phonetic": "uː",
            "position": 8,
            "confidence": 0.85,
            "stress_level": 0
          },
          {
            "text": "шӣ",
            "weight": "SyllableWeight.HEAVY",
            "phonetic": "ʃiː",
            "position": 9,
            "confidence": 0.85,
            "stress_level": 2
          }
        ],
        [
          {
            "text": "и",
            "weight": "SyllableWeight.LIGHT",
            "phonetic": "i",
            "position": 0,
            "confidence": 0.85,
            "stress_level": 2
          },
          {
            "text": "ҳат",
            "weight": "SyllableWeight.HEAVY",
            "phonetic": "hat",
            "position": 1,
            "confidence": 0.85,
            "stress_level": 0
          },
          {
            "text": "ти",
            "weight": "SyllableWeight.LIGHT",
            "phonetic": "ti",
            "position": 2,
            "confidence": 0.85,
            "stress_level": 2
          },
          {
            "text": "со",
            "weight": "SyllableWeight.LIGHT",
            "phonetic": "so",
            "position": 3,
            "confidence": 0.85,
            "stress_level": 0
          },
          {
            "text": "яр",
            "weight": "SyllableWeight.HEAVY",
            "phonetic": "jar",
            "position": 4,
            "confidence": 0.85,
            "stress_level": 0
          },
          {
            "text": "ан",
            "weight": "SyllableWeight.HEAVY",
            "phonetic": "an",
            "position": 5,
            "confidence": 0.85,
            "stress_level": 0
          },
          {
            "text": "ге",
            "weight": "SyllableWeight.LIGHT",
            "phonetic": "ge",
            "position": 6,
            "confidence": 0.85,
            "stress_level": 2
          },
          {
            "text": "дар",
            "weight": "SyllableWeight.HEAVY",
            "phonetic": "dar",
            "position": 7,
            "confidence": 0.85,
            "stress_level": 2
          },
          {
            "text": "ча",
            "weight": "SyllableWeight.LIGHT",
            "phonetic": "ʧa",
            "position": 8,
            "confidence": 0.85,
            "stress_level": 0
          },
          {
            "text": "бин",
            "weight": "SyllableWeight.HEAVY",
            "phonetic": "bin",
            "position": 9,
            "confidence": 0.85,
            "stress_level": 0
          },
          {
            "text": "ам",
            "weight": "SyllableWeight.HEAVY",
            "phonetic": "am",
            "position": 10,
            "confidence": 0.85,
            "stress_level": 2
          }
        ],
        [
          {
            "text": "ав",
            "weight": "SyllableWeight.HEAVY",
            "phonetic": "av",
            "position": 0,
            "confidence": 0.85,
            "stress_level": 0
          },
          {
            "text": "о",
            "weight": "SyllableWeight.LIGHT",
            "phonetic": "o",
            "position": 1,
            "confidence": 0.85,
            "stress_level": 0
          },
          {
            "text": "и",
            "weight": "SyllableWeight.LIGHT",
            "phonetic": "i",
            "position": 2,
            "confidence": 0.85,
            "stress_level": 2
          },
          {
            "text": "ҳас",
            "weight": "SyllableWeight.HEAVY",
            "phonetic": "has",
            "position": 3,
            "confidence": 0.85,
            "stress_level": 0
          },
          {
            "text": "та",
            "weight": "SyllableWeight.LIGHT",
            "phonetic": "ta",
            "position": 4,
            "confidence": 0.85,
            "stress_level": 2
          },
          {
            "text": "бор",
            "weight": "SyllableWeight.HEAVY",
            "phonetic": "bor",
            "position": 5,
            "confidence": 0.85,
            "stress_level": 0
          },
          {
            "text": "он",
            "weight": "SyllableWeight.HEAVY",
            "phonetic": "on",
            "position": 6,
            "confidence": 0.85,
            "stress_level": 0
          },
          {
            "text": "и",
            "weight": "SyllableWeight.LIGHT",
            "phonetic": "i",
            "position": 7,
            "confidence": 0.85,
            "stress_level": 2
          },
          {
            "text": "ҳа",
            "weight": "SyllableWeight.LIGHT",
            "phonetic": "ha",
            "position": 8,
            "confidence": 0.85,
            "stress_level": 0
          },
          {
            "text": "зин",
            "weight": "SyllableWeight.HEAVY",
            "phonetic": "zin",
            "position": 9,
            "confidence": 0.85,
            "stress_level": 0
          },
          {
            "text": "ам",
            "weight": "SyllableWeight.HEAVY",
            "phonetic": "am",
            "position": 10,
            "confidence": 0.85,
            "stress_level": 2
          }
        ],
        [
          {
            "text": "и",
            "weight": "SyllableWeight.LIGHT",
            "phonetic": "i",
            "position": 0,
            "confidence": 0.85,
            "stress_level": 2
          },
          {
            "text": "фар",
            "weight": "SyllableWeight.HEAVY",
            "phonetic": "far",
            "position": 1,
            "confidence": 0.85,
            "stress_level": 0
          },
          {
            "text": "до",
            "weight": "SyllableWeight.LIGHT",
            "phonetic": "do",
            "position": 2,
            "confidence": 0.85,
            "stress_level": 0
          },
          {
            "text": "ҳо",
            "weight": "SyllableWeight.LIGHT",
            "phonetic": "ho",
            "position": 3,
            "confidence": 0.85,
            "stress_level": 2
          },
          {
            "text": "чи",
            "weight": "SyllableWeight.LIGHT",
            "phonetic": "ʧi",
            "position": 4,
            "confidence": 0.85,
            "stress_level": 2
          },
          {
            "text": "ме",
            "weight": "SyllableWeight.LIGHT",
            "phonetic": "me",
            "position": 5,
            "confidence": 0.85,
            "stress_level": 0
          },
          {
            "text": "пур",
            "weight": "SyllableWeight.HEAVY",
            "phonetic": "pur",
            "position": 6,
            "confidence": 0.85,
            "stress_level": 0
          },
          {
            "text": "сӣ",
            "weight": "SyllableWeight.HEAVY",
            "phonetic": "siː",
            "position": 7,
            "confidence": 0.85,
            "stress_level": 2
          },
          {
            "text": "сур",
            "weight": "SyllableWeight.HEAVY",
            "phonetic": "sur",
            "position": 8,
            "confidence": 0.85,
            "stress_level": 0
          },
          {
            "text": "о",
            "weight": "SyllableWeight.LIGHT",
            "phonetic": "o",
            "position": 9,
            "confidence": 0.85,
            "stress_level": 0
          },
          {
            "text": "гам",
            "weight": "SyllableWeight.HEAVY",
            "phonetic": "gam",
            "position": 10,
            "confidence": 0.85,
            "stress_level": 2
          }
        ],
        [
          {
            "text": "ир",
            "weight": "SyllableWeight.HEAVY",
            "phonetic": "ir",
            "position": 0,
            "confidence": 0.85,
            "stress_level": 0
          },
          {
            "text": "еҳ",
            "weight": "SyllableWeight.HEAVY",
            "phonetic": "eh",
            "position": 1,
            "confidence": 0.85,
            "stress_level": 2
          },
          {
            "text": "ан",
            "weight": "SyllableWeight.HEAVY",
            "phonetic": "an",
            "position": 2,
            "confidence": 0.85,
            "stress_level": 0
          },
          {
            "text": "дар",
            "weight": "SyllableWeight.HEAVY",
            "phonetic": "dar",
            "position": 3,
            "confidence": 0.85,
            "stress_level": 2
          },
          {
            "text": "на",
            "weight": "SyllableWeight.LIGHT",
            "phonetic": "na",
            "position": 4,
            "confidence": 0.85,
            "stress_level": 0
          },
          {
            "text": "фас",
            "weight": "SyllableWeight.HEAVY",
            "phonetic": "fas",
            "position": 5,
            "confidence": 0.85,
            "stress_level": 0
          },
          {
            "text": "ҳо",
            "weight": "SyllableWeight.LIGHT",
            "phonetic": "ho",
            "position": 6,
            "confidence": 0.85,
            "stress_level": 0
          },
          {
            "text": "и",
            "weight": "SyllableWeight.LIGHT",
            "phonetic": "i",
            "position": 7,
            "confidence": 0.85,
            "stress_level": 2
          },
          {
            "text": "зам",
            "weight": "SyllableWeight.HEAVY",
            "phonetic": "zam",
            "position": 8,
            "confidence": 0.85,
            "stress_level": 0
          },
          {
            "text": "ин",
            "weight": "SyllableWeight.HEAVY",
            "phonetic": "in",
            "position": 9,
            "confidence": 0.85,
            "stress_level": 0
          },
          {
            "text": "ам",
            "weight": "SyllableWeight.HEAVY",
            "phonetic": "am",
            "position": 10,
            "confidence": 0.85,
            "stress_level": 2
          }
        ],
        [
          {
            "text": "и",
            "weight": "SyllableWeight.LIGHT",
            "phonetic": "i",
            "position": 0,
            "confidence": 0.85,
            "stress_level": 2
          },
          {
            "text": "ме",
            "weight": "SyllableWeight.LIGHT",
            "phonetic": "me",
            "position": 1,
            "confidence": 0.85,
            "stress_level": 0
          },
          {
            "text": "гӯй",
            "weight": "SyllableWeight.HEAVY",
            "phonetic": "guːj",
            "position": 2,
            "confidence": 0.85,
            "stress_level": 2
          },
          {
            "text": "ту",
            "weight": "SyllableWeight.LIGHT",
            "phonetic": "tu",
            "position": 3,
            "confidence": 0.85,
            "stress_level": 2
          },
          {
            "text": "бо",
            "weight": "SyllableWeight.LIGHT",
            "phonetic": "bo",
            "position": 4,
            "confidence": 0.85,
            "stress_level": 0
          },
          {
            "text": "зор",
            "weight": "SyllableWeight.HEAVY",
            "phonetic": "zor",
            "position": 5,
            "confidence": 0.85,
            "stress_level": 0
          },
          {
            "text": "и",
            "weight": "SyllableWeight.LIGHT",
            "phonetic": "i",
            "position": 6,
            "confidence": 0.85,
            "stress_level": 2
          },
          {
            "text": "зам",
            "weight": "SyllableWeight.HEAVY",
            "phonetic": "zam",
            "position": 7,
            "confidence": 0.85,
            "stress_level": 0
          },
          {
            "text": "онр",
            "weight": "SyllableWeight.HEAVY",
            "phonetic": "onr",
            "position": 8,
            "confidence": 0.85,
            "stress_level": 0
          },
          {
            "text": "о",
            "weight": "SyllableWeight.LIGHT",
            "phonetic": "o",
            "position": 9,
            "confidence": 0.85,
            "stress_level": 2
          }
        ],
        [
          {
            "text": "а",
            "weight": "SyllableWeight.LIGHT",
            "phonetic": "a",
            "position": 0,
            "confidence": 0.85,
            "stress_level": 0
          },
          {
            "text": "ши",
            "weight": "SyllableWeight.LIGHT",
            "phonetic": "ʃi",
            "position": 1,
            "confidence": 0.85,
            "stress_level": 0
          },
          {
            "text": "зи",
            "weight": "SyllableWeight.LIGHT",
            "phonetic": "zi",
            "position": 2,
            "confidence": 0.85,
            "stress_level": 2
          },
          {
            "text": "бе",
            "weight": "SyllableWeight.LIGHT",
            "phonetic": "be",
            "position": 3,
            "confidence": 0.85,
            "stress_level": 0
          },
          {
            "text": "ба",
            "weight": "SyllableWeight.LIGHT",
            "phonetic": "ba",
            "position": 4,
            "confidence": 0.85,
            "stress_level": 0
          },
          {
            "text": "ҳо",
            "weight": "SyllableWeight.LIGHT",
            "phonetic": "ho",
            "position": 5,
            "confidence": 0.85,
            "stress_level": 2
          },
          {
            "text": "пе",
            "weight": "SyllableWeight.LIGHT",
            "phonetic": "pe",
            "position": 6,
            "confidence": 0.85,
            "stress_level": 0
          },
          {
            "text": "ши",
            "weight": "SyllableWeight.LIGHT",
            "phonetic": "ʃi",
            "position": 7,
            "confidence": 0.85,
            "stress_level": 2
          },
          {
            "text": "ни",
            "weight": "SyllableWeight.LIGHT",
            "phonetic": "ni",
            "position": 8,
            "confidence": 0.85,
            "stress_level": 0
          },
          {
            "text": "гин",
            "weight": "SyllableWeight.HEAVY",
            "phonetic": "gin",
            "position": 9,
            "confidence": 0.85,
            "stress_level": 0
          },
          {
            "text": "ам",
            "weight": "SyllableWeight.HEAVY",
            "phonetic": "am",
            "position": 10,
            "confidence": 0.85,
            "stress_level": 2
          }
        ],
        [
          {
            "text": "а",
            "weight": "SyllableWeight.LIGHT",
            "phonetic": "a",
            "position": 0,
            "confidence": 0.85,
            "stress_level": 2
          },
          {
            "text": "лаб",
            "weight": "SyllableWeight.HEAVY",
            "phonetic": "lab",
            "position": 1,
            "confidence": 0.85,
            "stress_level": 0
          },
          {
            "text": "хан",
            "weight": "SyllableWeight.HEAVY",
            "phonetic": "xan",
            "position": 2,
            "confidence": 0.85,
            "stress_level": 0
          },
          {
            "text": "а",
            "weight": "SyllableWeight.LIGHT",
            "phonetic": "a",
            "position": 3,
            "confidence": 0.85,
            "stress_level": 0
          },
          {
            "text": "дев",
            "weight": "SyllableWeight.HEAVY",
            "phonetic": "dev",
            "position": 4,
            "confidence": 0.85,
            "stress_level": 0
          },
          {
            "text": "у",
            "weight": "SyllableWeight.LIGHT",
            "phonetic": "u",
            "position": 5,
            "confidence": 0.85,
            "stress_level": 2
          },
          {
            "text": "гарм",
            "weight": "SyllableWeight.HEAVY",
            "phonetic": "garm",
            "position": 6,
            "confidence": 0.85,
            "stress_level": 0
          },
          {
            "text": "о",
            "weight": "SyllableWeight.LIGHT",
            "phonetic": "o",
            "position": 7,
            "confidence": 0.85,
            "stress_level": 0
          },
          {
            "text": "е",
            "weight": "SyllableWeight.LIGHT",
            "phonetic": "e",
            "position": 8,
            "confidence": 0.85,
            "stress_level": 2
          },
          {
            "text": "на",
            "weight": "SyllableWeight.LIGHT",
            "phonetic": "na",
            "position": 9,
            "confidence": 0.85,
            "stress_level": 2
          },
          {
            "text": "иш",
            "weight": "SyllableWeight.HEAVY",
            "phonetic": "iʃ",
            "position": 10,
            "confidence": 0.85,
            "stress_level": 0
          },
          {
            "text": "қе",
            "weight": "SyllableWeight.LIGHT",
            "phonetic": "qe",
            "position": 11,
            "confidence": 0.85,
            "stress_level": 2
          }
        ],
        [
          {
            "text": "ам",
            "weight": "SyllableWeight.HEAVY",
            "phonetic": "am",
            "position": 0,
            "confidence": 0.85,
            "stress_level": 0
          },
          {
            "text": "ин",
            "weight": "SyllableWeight.HEAVY",
            "phonetic": "in",
            "position": 1,
            "confidence": 0.85,
            "stress_level": 2
          },
          {
            "text": "дард",
            "weight": "SyllableWeight.HEAVY",
            "phonetic": "dard",
            "position": 2,
            "confidence": 0.85,
            "stress_level": 2
          },
          {
            "text": "аст",
            "weight": "SyllableWeight.HEAVY",
            "phonetic": "ast",
            "position": 3,
            "confidence": 0.85,
            "stress_level": 2
          },
          {
            "text": "гӯ",
            "weight": "SyllableWeight.HEAVY",
            "phonetic": "guː",
            "position": 4,
            "confidence": 0.85,
            "stress_level": 0
          },
          {
            "text": "ё",
            "weight": "SyllableWeight.LIGHT",
            "phonetic": "jo",
            "position": 5,
            "confidence": 0.85,
            "stress_level": 2
          },
          {
            "text": "дар",
            "weight": "SyllableWeight.HEAVY",
            "phonetic": "dar",
            "position": 6,
            "confidence": 0.85,
            "stress_level": 2
          },
          {
            "text": "кам",
            "weight": "SyllableWeight.HEAVY",
            "phonetic": "kam",
            "position": 7,
            "confidence": 0.85,
            "stress_level": 0
          },
          {
            "text": "ин",
            "weight": "SyllableWeight.HEAVY",
            "phonetic": "in",
            "position": 8,
            "confidence": 0.85,
            "stress_level": 0
          },
          {
            "text": "ам",
            "weight": "SyllableWeight.HEAVY",
            "phonetic": "am",
            "position": 9,
            "confidence": 0.85,
            "stress_level": 2
          }
        ],
        [
          {
            "text": "а",
            "weight": "SyllableWeight.LIGHT",
            "phonetic": "a",
            "position": 0,
            "confidence": 0.85,
            "stress_level": 2
          },
          {
            "text": "ин",
            "weight": "SyllableWeight.HEAVY",
            "phonetic": "in",
            "position": 1,
            "confidence": 0.85,
            "stress_level": 2
          },
          {
            "text": "бол",
            "weight": "SyllableWeight.HEAVY",
            "phonetic": "bol",
            "position": 2,
            "confidence": 0.85,
            "stress_level": 0
          },
          {
            "text": "ев",
            "weight": "SyllableWeight.HEAVY",
            "phonetic": "ev",
            "position": 3,
            "confidence": 0.85,
            "stress_level": 0
          },
          {
            "text": "у",
            "weight": "SyllableWeight.LIGHT",
            "phonetic": "u",
            "position": 4,
            "confidence": 0.85,
            "stress_level": 2
          },
          {
            "text": "парв",
            "weight": "SyllableWeight.HEAVY",
            "phonetic": "parv",
            "position": 5,
            "confidence": 0.85,
            "stress_level": 0
          },
          {
            "text": "о",
            "weight": "SyllableWeight.LIGHT",
            "phonetic": "o",
            "position": 6,
            "confidence": 0.85,
            "stress_level": 0
          },
          {
            "text": "зе",
            "weight": "SyllableWeight.LIGHT",
            "phonetic": "ze",
            "position": 7,
            "confidence": 0.85,
            "stress_level": 2
          },
          {
            "text": "ки",
            "weight": "SyllableWeight.LIGHT",
            "phonetic": "ki",
            "position": 8,
            "confidence": 0.85,
            "stress_level": 2
          },
          {
            "text": "дор",
            "weight": "SyllableWeight.HEAVY",
            "phonetic": "dor",
            "position": 9,
            "confidence": 0.85,
            "stress_level": 0
          },
          {
            "text": "ам",
            "weight": "SyllableWeight.HEAVY",
            "phonetic": "am",
            "position": 10,
            "confidence": 0.85,
            "stress_level": 2
          }
        ],
        [
          {
            "text": "у",
            "weight": "SyllableWeight.LIGHT",
            "phonetic": "u",
            "position": 0,
            "confidence": 0.85,
            "stress_level": 0
          },
          {
            "text": "ҷо",
            "weight": "SyllableWeight.LIGHT",
            "phonetic": "ʤo",
            "position": 1,
            "confidence": 0.85,
            "stress_level": 2
          },
          {
            "text": "бол",
            "weight": "SyllableWeight.HEAVY",
            "phonetic": "bol",
            "position": 2,
            "confidence": 0.85,
            "stress_level": 0
          },
          {
            "text": "о",
            "weight": "SyllableWeight.LIGHT",
            "phonetic": "o",
            "position": 3,
            "confidence": 0.85,
            "stress_level": 2
          },
          {
            "text": "ҳан",
            "weight": "SyllableWeight.HEAVY",
            "phonetic": "han",
            "position": 4,
            "confidence": 0.85,
            "stress_level": 0
          },
          {
            "text": "ӯ",
            "weight": "SyllableWeight.HEAVY",
            "phonetic": "uː",
            "position": 5,
            "confidence": 0.85,
            "stress_level": 0
          },
          {
            "text": "зам",
            "weight": "SyllableWeight.HEAVY",
            "phonetic": "zam",
            "position": 6,
            "confidence": 0.85,
            "stress_level": 2
          },
          {
            "text": "дар",
            "weight": "SyllableWeight.HEAVY",
            "phonetic": "dar",
            "position": 7,
            "confidence": 0.85,
            "stress_level": 2
          },
          {
            "text": "зам",
            "weight": "SyllableWeight.HEAVY",
            "phonetic": "zam",
            "position": 8,
            "confidence": 0.85,
            "stress_level": 0
          },
          {
            "text": "ин",
            "weight": "SyllableWeight.HEAVY",
            "phonetic": "in",
            "position": 9,
            "confidence": 0.85,
            "stress_level": 0
          },
          {
            "text": "ам",
            "weight": "SyllableWeight.HEAVY",
            "phonetic": "am",
            "position": 10,
            "confidence": 0.85,
            "stress_level": 2
          }
        ],
        [
          {
            "text": "ур",
            "weight": "SyllableWeight.HEAVY",
            "phonetic": "ur",
            "position": 0,
            "confidence": 0.85,
            "stress_level": 0
          },
          {
            "text": "о",
            "weight": "SyllableWeight.LIGHT",
            "phonetic": "o",
            "position": 1,
            "confidence": 0.85,
            "stress_level": 0
          },
          {
            "text": "гӣ",
            "weight": "SyllableWeight.HEAVY",
            "phonetic": "giː",
            "position": 2,
            "confidence": 0.85,
            "stress_level": 2
          },
          {
            "text": "осм",
            "weight": "SyllableWeight.HEAVY",
            "phonetic": "osm",
            "position": 3,
            "confidence": 0.85,
            "stress_level": 0
          },
          {
            "text": "он",
            "weight": "SyllableWeight.HEAVY",
            "phonetic": "on",
            "position": 4,
            "confidence": 0.85,
            "stress_level": 0
          },
          {
            "text": "и",
            "weight": "SyllableWeight.LIGHT",
            "phonetic": "i",
            "position": 5,
            "confidence": 0.85,
            "stress_level": 2
          },
          {
            "text": "ин",
            "weight": "SyllableWeight.HEAVY",
            "phonetic": "in",
            "position": 6,
            "confidence": 0.85,
            "stress_level": 0
          },
          {
            "text": "ти",
            "weight": "SyllableWeight.LIGHT",
            "phonetic": "ti",
            "position": 7,
            "confidence": 0.85,
            "stress_level": 0
          },
          {
            "text": "ҳо",
            "weight": "SyllableWeight.LIGHT",
            "phonetic": "ho",
            "position": 8,
            "confidence": 0.85,
            "stress_level": 2
          },
          {
            "text": "ку",
            "weight": "SyllableWeight.LIGHT",
            "phonetic": "ku",
            "position": 9,
            "confidence": 0.85,
            "stress_level": 2
          }
        ],
        [
          {
            "text": "ан",
            "weight": "SyllableWeight.HEAVY",
            "phonetic": "an",
            "position": 0,
            "confidence": 0.85,
            "stress_level": 0
          },
          {
            "text": "ӯ",
            "weight": "SyllableWeight.HEAVY",
            "phonetic": "uː",
            "position": 1,
            "confidence": 0.85,
            "stress_level": 0
          },
          {
            "text": "зам",
            "weight": "SyllableWeight.HEAVY",
            "phonetic": "zam",
            "position": 2,
            "confidence": 0.85,
            "stress_level": 2
          },
          {
            "text": "зарр",
            "weight": "SyllableWeight.HEAVY",
            "phonetic": "zarr",
            "position": 3,
            "confidence": 0.85,
            "stress_level": 0
          },
          {
            "text": "а",
            "weight": "SyllableWeight.LIGHT",
            "phonetic": "a",
            "position": 4,
            "confidence": 0.85,
            "stress_level": 0
          },
          {
            "text": "и",
            "weight": "SyllableWeight.LIGHT",
            "phonetic": "i",
            "position": 5,
            "confidence": 0.85,
            "stress_level": 2
          },
          {
            "text": "хо",
            "weight": "SyllableWeight.LIGHT",
            "phonetic": "xo",
            "position": 6,
            "confidence": 0.85,
            "stress_level": 0
          },
          {
            "text": "ки",
            "weight": "SyllableWeight.LIGHT",
            "phonetic": "ki",
            "position": 7,
            "confidence": 0.85,
            "stress_level": 2
          },
          {
            "text": "қа",
            "weight": "SyllableWeight.LIGHT",
            "phonetic": "qa",
            "position": 8,
            "confidence": 0.85,
            "stress_level": 0
          },
          {
            "text": "дим",
            "weight": "SyllableWeight.HEAVY",
            "phonetic": "dim",
            "position": 9,
            "confidence": 0.85,
            "stress_level": 0
          },
          {
            "text": "ам",
            "weight": "SyllableWeight.HEAVY",
            "phonetic": "am",
            "position": 10,
            "confidence": 0.85,
            "stress_level": 2
          }
        ],
        [
          {
            "text": "ур",
            "weight": "SyllableWeight.HEAVY",
            "phonetic": "ur",
            "position": 0,
            "confidence": 0.85,
            "stress_level": 0
          },
          {
            "text": "у",
            "weight": "SyllableWeight.LIGHT",
            "phonetic": "u",
            "position": 1,
            "confidence": 0.85,
            "stress_level": 0
          },
          {
            "text": "би",
            "weight": "SyllableWeight.LIGHT",
            "phonetic": "bi",
            "position": 2,
            "confidence": 0.85,
            "stress_level": 2
          },
          {
            "text": "лол",
            "weight": "SyllableWeight.HEAVY",
            "phonetic": "lol",
            "position": 3,
            "confidence": 0.85,
            "stress_level": 0
          },
          {
            "text": "а",
            "weight": "SyllableWeight.LIGHT",
            "phonetic": "a",
            "position": 4,
            "confidence": 0.85,
            "stress_level": 0
          },
          {
            "text": "и",
            "weight": "SyllableWeight.LIGHT",
            "phonetic": "i",
            "position": 5,
            "confidence": 0.85,
            "stress_level": 2
          },
          {
            "text": "сабр",
            "weight": "SyllableWeight.HEAVY",
            "phonetic": "sabr",
            "position": 6,
            "confidence": 0.85,
            "stress_level": 0
          },
          {
            "text": "и",
            "weight": "SyllableWeight.LIGHT",
            "phonetic": "i",
            "position": 7,
            "confidence": 0.85,
            "stress_level": 2
          },
          {
            "text": "ман",
            "weight": "SyllableWeight.HEAVY",
            "phonetic": "man",
            "position": 8,
            "confidence": 0.85,
            "stress_level": 2
          },
          {
            "text": "ин",
            "weight": "SyllableWeight.HEAVY",
            "phonetic": "in",
            "position": 9,
            "confidence": 0.85,
            "stress_level": 2
          },
          {
            "text": "аст",
            "weight": "SyllableWeight.HEAVY",
            "phonetic": "ast",
            "position": 10,
            "confidence": 0.85,
            "stress_level": 2
          }
        ],
        [
          {
            "text": "и",
            "weight": "SyllableWeight.LIGHT",
            "phonetic": "i",
            "position": 0,
            "confidence": 0.85,
            "stress_level": 2
          },
          {
            "text": "ме",
            "weight": "SyllableWeight.LIGHT",
            "phonetic": "me",
            "position": 1,
            "confidence": 0.85,
            "stress_level": 0
          },
          {
            "text": "пур",
            "weight": "SyllableWeight.HEAVY",
            "phonetic": "pur",
            "position": 2,
            "confidence": 0.85,
            "stress_level": 0
          },
          {
            "text": "сӣ",
            "weight": "SyllableWeight.HEAVY",
            "phonetic": "siː",
            "position": 3,
            "confidence": 0.85,
            "stress_level": 2
          },
          {
            "text": "чар",
            "weight": "SyllableWeight.HEAVY",
            "phonetic": "ʧar",
            "position": 4,
            "confidence": 0.85,
            "stress_level": 0
          },
          {
            "text": "о",
            "weight": "SyllableWeight.LIGHT",
            "phonetic": "o",
            "position": 5,
            "confidence": 0.85,
            "stress_level": 2
          },
          {
            "text": "ҳол",
            "weight": "SyllableWeight.HEAVY",
            "phonetic": "hol",
            "position": 6,
            "confidence": 0.85,
            "stress_level": 0
          },
          {
            "text": "о",
            "weight": "SyllableWeight.LIGHT",
            "phonetic": "o",
            "position": 7,
            "confidence": 0.85,
            "stress_level": 2
          },
          {
            "text": "чун",
            "weight": "SyllableWeight.HEAVY",
            "phonetic": "ʧun",
            "position": 8,
            "confidence": 0.85,
            "stress_level": 0
          },
          {
            "text": "ин",
            "weight": "SyllableWeight.HEAVY",
            "phonetic": "in",
            "position": 9,
            "confidence": 0.85,
            "stress_level": 0
          },
          {
            "text": "ам",
            "weight": "SyllableWeight.HEAVY",
            "phonetic": "am",
            "position": 10,
            "confidence": 0.85,
            "stress_level": 2
          }
        ]
      ],
      "aruz_analysis": {
        "identified_meter": "ṭawīl",
        "pattern_match": "U—UUUU—UU",
        "confidence": "MeterConfidence.HIGH",
        "pattern_accuracy": 0.8888888888888888,
        "variations_detected": [
          "U—UU—U—UU",
          "U—UU—U—U—"
        ],
        "line_scansion": [
          {
            "text": "ба",
            "weight": "SyllableWeight.LIGHT",
            "phonetic": "ba",
            "position": 0,
            "confidence": 0.85,
            "stress_level": 2
          },
          {
            "text": "ир",
            "weight": "SyllableWeight.HEAVY",
            "phonetic": "ir",
            "position": 1,
            "confidence": 0.85,
            "stress_level": 0
          },
          {
            "text": "ти",
            "weight": "SyllableWeight.LIGHT",
            "phonetic": "ti",
            "position": 2,
            "confidence": 0.85,
            "stress_level": 0
          },
          {
            "text": "бо",
            "weight": "SyllableWeight.LIGHT",
            "phonetic": "bo",
            "position": 3,
            "confidence": 0.85,
            "stress_level": 0
          },
          {
            "text": "ти",
            "weight": "SyllableWeight.LIGHT",
            "phonetic": "ti",
            "position": 4,
            "confidence": 0.85,
            "stress_level": 2
          },
          {
            "text": "ши",
            "weight": "SyllableWeight.LIGHT",
            "phonetic": "ʃi",
            "position": 5,
            "confidence": 0.85,
            "stress_level": 0
          },
          {
            "text": "кас",
            "weight": "SyllableWeight.HEAVY",
            "phonetic": "kas",
            "position": 6,
            "confidence": 0.85,
            "stress_level": 0
          },
          {
            "text": "та",
            "weight": "SyllableWeight.LIGHT",
            "phonetic": "ta",
            "position": 7,
            "confidence": 0.85,
            "stress_level": 0
          },
          {
            "text": "и",
            "weight": "SyllableWeight.LIGHT",
            "phonetic": "i",
            "position": 8,
            "confidence": 0.85,
            "stress_level": 2
          }
        ],
        "caesura_positions": []
      },
      "rhyme_scheme": [
        {
          "qafiyeh": "РОР",
          "radif": "",
          "phonetic_rhyme": "ror",
          "rhyme_type": "rich",
          "rhyme_position": "end",
          "confidence": 0.85
        },
        {
          "qafiyeh": "мад",
          "radif": "",
          "phonetic_rhyme": "mad",
          "rhyme_type": "rich",
          "rhyme_position": "end",
          "confidence": 0.85
        },
        {
          "qafiyeh": "ман",
          "radif": "",
          "phonetic_rhyme": "man",
          "rhyme_type": "rich",
          "rhyme_position": "end",
          "confidence": 0.85
        },
        {
          "qafiyeh": "зад",
          "radif": "",
          "phonetic_rhyme": "zad",
          "rhyme_type": "rich",
          "rhyme_position": "end",
          "confidence": 0.85
        },
        {
          "qafiyeh": "мад",
          "radif": "",
          "phonetic_rhyme": "mad",
          "rhyme_type": "rich",
          "rhyme_position": "end",
          "confidence": 0.85
        },
        {
          "qafiyeh": "ият",
          "radif": "",
          "phonetic_rhyme": "ijat",
          "rhyme_type": "rich",
          "rhyme_position": "end",
          "confidence": 0.85
        },
        {
          "qafiyeh": "ӯхт",
          "radif": "",
          "phonetic_rhyme": "uːxt",
          "rhyme_type": "rich",
          "rhyme_position": "end",
          "confidence": 0.85
        },
        {
          "qafiyeh": "ард",
          "radif": "",
          "phonetic_rhyme": "ard",
          "rhyme_type": "rich",
          "rhyme_position": "end",
          "confidence": 0.85
        },
        {
          "qafiyeh": "таи",
          "radif": "",
          "phonetic_rhyme": "tai",
          "rhyme_type": "rich",
          "rhyme_position": "end",
          "confidence": 0.85
        },
        {
          "qafiyeh": "ман",
          "radif": "бо ман",
          "phonetic_rhyme": "man",
          "rhyme_type": "rich",
          "rhyme_position": "end",
          "confidence": 0.85
        },
        {
          "qafiyeh": "дам",
          "radif": "",
          "phonetic_rhyme": "dam",
          "rhyme_type": "rich",
          "rhyme_position": "end",
          "confidence": 0.85
        },
        {
          "qafiyeh": "нам",
          "radif": "",
          "phonetic_rhyme": "nam",
          "rhyme_type": "rich",
          "rhyme_position": "end",
          "confidence": 0.85
        },
        {
          "qafiyeh": "арг",
          "radif": "",
          "phonetic_rhyme": "arg",
          "rhyme_type": "rich",
          "rhyme_position": "end",
          "confidence": 0.85
        },
        {
          "qafiyeh": "онд",
          "radif": "",
          "phonetic_rhyme": "ond",
          "rhyme_type": "rich",
          "rhyme_position": "end",
          "confidence": 0.85
        },
        {
          "qafiyeh": "шон",
          "radif": "",
          "phonetic_rhyme": "ʃon",
          "rhyme_type": "rich",
          "rhyme_position": "end",
          "confidence": 0.85
        },
        {
          "qafiyeh": "мад",
          "radif": "",
          "phonetic_rhyme": "mad",
          "rhyme_type": "rich",
          "rhyme_position": "end",
          "confidence": 0.85
        },
        {
          "qafiyeh": "буд",
          "radif": "",
          "phonetic_rhyme": "bud",
          "rhyme_type": "rich",
          "rhyme_position": "end",
          "confidence": 0.85
        },
        {
          "qafiyeh": "ард",
          "radif": "",
          "phonetic_rhyme": "ard",
          "rhyme_type": "rich",
          "rhyme_position": "end",
          "confidence": 0.85
        },
        {
          "qafiyeh": "ӯшӣ",
          "radif": "",
          "phonetic_rhyme": "uːʃiː",
          "rhyme_type": "rich",
          "rhyme_position": "end",
          "confidence": 0.85
        },
        {
          "qafiyeh": "нам",
          "radif": "",
          "phonetic_rhyme": "nam",
          "rhyme_type": "rich",
          "rhyme_position": "end",
          "confidence": 0.85
        },
        {
          "qafiyeh": "нам",
          "radif": "",
          "phonetic_rhyme": "nam",
          "rhyme_type": "rich",
          "rhyme_position": "end",
          "confidence": 0.85
        },
        {
          "qafiyeh": "гам",
          "radif": "",
          "phonetic_rhyme": "gam",
          "rhyme_type": "rich",
          "rhyme_position": "end",
          "confidence": 0.85
        },
        {
          "qafiyeh": "нам",
          "radif": "",
          "phonetic_rhyme": "nam",
          "rhyme_type": "rich",
          "rhyme_position": "end",
          "confidence": 0.85
        },
        {
          "qafiyeh": "нро",
          "radif": "",
          "phonetic_rhyme": "nro",
          "rhyme_type": "rich",
          "rhyme_position": "end",
          "confidence": 0.85
        },
        {
          "qafiyeh": "нам",
          "radif": "",
          "phonetic_rhyme": "nam",
          "rhyme_type": "rich",
          "rhyme_position": "end",
          "confidence": 0.85
        },
        {
          "qafiyeh": "шқе",
          "radif": "",
          "phonetic_rhyme": "ʃqe",
          "rhyme_type": "rich",
          "rhyme_position": "end",
          "confidence": 0.85
        },
        {
          "qafiyeh": "нам",
          "radif": "",
          "phonetic_rhyme": "nam",
          "rhyme_type": "rich",
          "rhyme_position": "end",
          "confidence": 0.85
        },
        {
          "qafiyeh": "рам",
          "radif": "",
          "phonetic_rhyme": "ram",
          "rhyme_type": "rich",
          "rhyme_position": "end",
          "confidence": 0.85
        },
        {
          "qafiyeh": "нам",
          "radif": "",
          "phonetic_rhyme": "nam",
          "rhyme_type": "rich",
          "rhyme_position": "end",
          "confidence": 0.85
        },
        {
          "qafiyeh": "ку",
          "radif": "",
          "phonetic_rhyme": "ku",
          "rhyme_type": "perfect",
          "rhyme_position": "end",
          "confidence": 0.85
        },
        {
          "qafiyeh": "мам",
          "radif": "",
          "phonetic_rhyme": "mam",
          "rhyme_type": "rich",
          "rhyme_position": "end",
          "confidence": 0.85
        },
        {
          "qafiyeh": "аст",
          "radif": "",
          "phonetic_rhyme": "ast",
          "rhyme_type": "rich",
          "rhyme_position": "end",
          "confidence": 0.85
        },
        {
          "qafiyeh": "нам",
          "radif": "",
          "phonetic_rhyme": "nam",
          "rhyme_type": "rich",
          "rhyme_position": "end",
          "confidence": 0.85
        }
      ],
      "rhyme_pattern": "free_rhyme_22unique",
      "stanza_structure": "free_verse",
      "avg_syllables": 8.64,
      "prosodic_consistency": 0.26487544295763477,
      "meter_confidence": "MeterConfidence.LOW",
      "modern_metrics": {
        "enjambement_count": 10,
        "enjambement_ratio": 0.3125,
        "semantic_density": 4.090909090909091,
        "line_length_variation": 0.4349992835986077,
        "prose_poetry_score": 0.23661904761904762,
        "visual_structure_score": 0.11627906976744186,
        "caesura_distribution": [
          1,
          4,
          10,
          15,
          17,
          19,
          21,
          23,
          25,
          26,
          27,
          28,
          31,
          32
        ],
        "syntactic_parallelism": 0.0,
        "lexical_repetition_score": 0.17307692307692307,
        "breath_group_length": 11.25,
        "pause_frequency": 0.9393939393939394
      },
      "is_free_verse": true,
      "free_verse_confidence": 0.5599999999999999,
      "modern_features": {
        "enjambement_density": 0.3125,
        "line_variation": 0.4349992835986077,
        "prose_tendency": 0.23661904761904762,
        "visual_complexity": 0.11627906976744186,
        "syntactic_parallelism": 0.0,
        "lexical_repetition": 0.17307692307692307
      }
    },
    "content": {
      "word_frequencies": [
        [
          "дар",
          6
        ],
        [
          "ки",
          4
        ],
        [
          "ман",
          4
        ],
        [
          "чи",
          4
        ],
        [
          "касе",
          3
        ],
        [
          "омад",
          3
        ],
        [
          "ту",
          3
        ],
        [
          "фирор",
          2
        ],
        [
          "ба",
          2
        ],
        [
          "бо",
          2
        ],
        [
          "марг",
          2
        ],
        [
          "ва",
          2
        ],
        [
          "мепурсӣ",
          2
        ],
        [
          "заминам",
          2
        ],
        [
          "на",
          2
        ],
        [
          "аст",
          2
        ],
        [
          "ин",
          2
        ],
        [
          "ҳанӯзам",
          2
        ],
        [
          "набзи",
          1
        ],
        [
          "садои",
          1
        ]
      ],
      "neologisms": [
        "болеву",
        "гармое",
        "заминам",
        "каминам",
        "лабханадеву",
        "мегӯй",
        "нигинам",
        "парвозе",
        "пашизи",
        "сояранге"
      ],
      "archaisms": [
        "ки",
        "андар",
        "зи"
      ],
      "theme_distribution": {
        "Love": 0,
        "Nature": 0,
        "Homeland": 0,
        "Religion": 0,
        "Mysticism": 0,
        "Philosophy": 0
      },
      "lexical_diversity": 0.77,
      "stylistic_register": "modern",
      "total_words": 135,
      "unique_words": 104
    },
    "literary": {
      "german_perspective": 2,
      "persian_tradition": 2,
      "tajik_elements": 1,
      "modernist_features": 5
    },
    "quality_metrics": {
      "quality_score": 0.8,
      "reliability": "medium",
      "warnings": [
        "Free verse detected - prosodic analysis limited"
      ],
      "recommendations": [
        "Check for textual corruption or free verse intention"
      ],
      "timestamp": "2026-01-18T03:00:50.614270",
      "free_verse_analysis": {
        "confidence": 0.5599999999999999,
        "enjambement_score": 0.3125,
        "prose_poetry_score": 0.23661904761904762,
        "line_variation_score": 0.4349992835986077,
        "assessment": "excellent_free_verse"
      }
    }
  },
  "tags": [
    "meter:ṭawīl",
    "form:free_verse",
    "register:modern",
    "form:free_verse",
    "radif:бо ман"
  ]
}